AUTHORS
CHANGES
ChangeLog
EweeStats.py
MANIFEST.in
eweestats
setup.cfg
setup.py
EweeStats/Adafruit_CharLCDPlate.py
EweeStats/Adafruit_I2C.py
EweeStats/AnalogGraphThreads.py
EweeStats/__init__.py
EweeStats/__main__.py
EweeStats/convert_data.py
EweeStats/create_files.py
EweeStats/graph.py
EweeStats/ods.py
EweeStats/pinselection.py
EweeStats/readconfig.py
EweeStats.egg-info/PKG-INFO
EweeStats.egg-info/SOURCES.txt
EweeStats.egg-info/dependency_links.txt
EweeStats.egg-info/requires.txt
EweeStats.egg-info/top_level.txt
cfg/eweestats.conf