Metadata-Version: 1.0
Name: EweeStats
Version: 0.0-alpha.2
Summary: Program to read, process, present and broadcast datas from sensors
Home-page: https://github.com/gabrielhdt/github
Author: Gabriel Hondet
Author-email: gabrielhondet@gmail.com
License: GPL 3
Platform: POSIX
